tauri_reader-0.1.4.dist-info/METADATA
tauri_reader-0.1.4.dist-info/WHEEL
tauri_reader-0.1.4.dist-info/entry_points.txt
tauri_reader-0.1.4.dist-info/licenses/LICENSE
tauri_reader/__init__.py
tauri_reader/__main__.py
tauri_reader-0.1.4.dist-info/RECORD
