Metadata-Version: 2.1
Name: tauri-reader
Version: 0.1.4
Summary: tauri static asset extraction gadget
Author-Email: hacbit <hacbit@foxmail.com>
License: MIT
Requires-Python: >=3.10
Requires-Dist: brotli>=1.1.0
